{"OOV": 1, "terima": 2, "kasih": 3, "tidak": 4, "sudah": 5, "cepat": 6, "dan": 7, "enak": 8, "yang": 9, "beli": 10, "nya": 11, "pengiriman": 12, "sampai": 13, "tapi": 14, "barang": 15, "banget": 16, "penjual": 17, "sesuai": 18, "saya": 19, "dengan": 20, "pengemasan": 21, "di": 22, "respons": 23, "ini": 24, "rasa": 25, "ada": 26, "baik": 27, "ya": 28, "mantap": 29, "bagus": 30, "jadi": 31, "juga": 32, "selalu": 33, "kurang": 34, "agak": 35, "rapi": 36, "pesanan": 37, "lagi": 38, "untuk": 39, "rasanya": 40, "aman": 41, "produk": 42, "dari": 43, "ok": 44, "belum": 45, "karena": 46, "kali": 47, "rekomendasi": 48, "sama": 49, "kalau": 50, "sangat": 51, "disini": 52, "cuma": 53, "hari": 54, "saja": 55, "lama": 56, "bisa": 57, "diterima": 58, "banyak": 59, "suka": 60, "hancur": 61, "masih": 62, "semoga": 63, "seperti": 64, "ke": 65, "puas": 66, "langanan": 67, "datang": 68, "dikirim": 69, "oke": 70, "pesan": 71, "lebih": 72, "baru": 73, "segar": 74, "pas": 75, "manis": 76, "harga": 77, "lumayan": 78, "pelayanan": 79, "ramah": 80, "terlalu": 81, "buat": 82, "sedikit": 83, "paket": 84, "sekali": 85, "kualitas": 86, "kemasan": 87, "asli": 88, "kadaluarsa": 89, "sukses": 90, "biasa": 91, "kue": 92, "terus": 93, "deskripsi": 94, "pakai": 95, "sayang": 96, "dicoba": 97, "semua": 98, "toko": 99, "mungkin": 100, "sih": 101, "alhamdulillah": 102, "mau": 103, "padahal": 104, "jam": 105, "belanja": 106, "deh": 107, "proses": 108, "bintang": 109, "tanggal": 110, "kak": 111, "hanya": 112, "kimchi": 113, "dalam": 114, "buble": 115, "isi": 116, "dapat": 117, "ternyata": 118, "kesekian": 119, "walaupun": 120, "kecewa": 121, "top": 122, "langsung": 123, "renyah": 124, "kurir": 125, "memang": 126, "waktu": 127, "ulang": 128, "ikan": 129, "kardus": 130, "makan": 131, "kecil": 132, "kalinya": 133, "dulu": 134, "beda": 135, "lah": 136, "pembelian": 137, "selamat": 138, "sore": 139, "terbaik": 140, "kirim": 141, "bukan": 142, "dimakan": 143, "plastik": 144, "the": 145, "kacang": 146, "kering": 147, "wrap": 148, "pertama": 149, "besar": 150, "cocok": 151, "admin": 152, "aku": 153, "bawang": 154, "lain": 155, "lambat": 156, "gurih": 157, "kemarin": 158, "kuenya": 159, "sepertinya": 160, "tahu": 161, "setelah": 162, "pokoknya": 163, "lanjut": 164, "kamu": 165, "coba": 166, "kondisi": 167, "berapa": 168, "pagi": 169, "agan": 170, "harus": 171, "anak": 172, "pernah": 173, "habis": 174, "sendiri": 175, "malam": 176, "rusak": 177, "murah": 178, "berasa": 179, "sini": 180, "atau": 181, "akan": 182, "itu": 183, "super": 184, "bonus": 185, "siang": 186, "buka": 187, "garing": 188, "bungkus": 189, "chat": 190, "sat": 191, "maaf": 192, "keripik": 193, "asin": 194, "paling": 195, "mencoba": 196, "pasti": 197, "keras": 198, "menurut": 199, "memuaskan": 200, "pedas": 201, "lembut": 202, "penyok": 203, "jauh": 204, "kg": 205, "harapan": 206, "rumah": 207, "tebal": 208, "hehe": 209, "yah": 210, "minta": 211, "dibuka": 212, "bau": 213, "produknya": 214, "ongkir": 215, "puasa": 216, "kira": 217, "minum": 218, "sering": 219, "terasa": 220, "dikasih": 221, "kok": 222, "benar": 223, "wangi": 224, "dua": 225, "satu": 226, "cukup": 227, "bocor": 228, "beberapa": 229, "kiriman": 230, "kedua": 231, "biasanya": 232, "tetap": 233, "favorit": 234, "luar": 235, "jangan": 236, "gr": 237, "kerja": 238, "keren": 239, "makanan": 240, "berkali": 241, "pahit": 242, "biar": 243, "kembali": 244, "salah": 245, "sebelum": 246, "eh": 247, "gitu": 248, "orang": 249, "amanah": 250, "bos": 251, "keseluruhan": 252, "akhirnya": 253, "gratis": 254, "foto": 255, "apa": 256, "utuh": 257, "an": 258, "pun": 259, "melempem": 260, "sekarang": 261, "remuk": 262, "parah": 263, "pecah": 264, "ulasan": 265, "tolong": 266, "kenapa": 267, "kotak": 268, "teman": 269, "kaya": 270, "tinggal": 271, "katanya": 272, "asam": 273, "ganti": 274, "pembungkus": 275, "varian": 276, "selera": 277, "mohon": 278, "meski": 279, "kelihatan": 280, "kami": 281, "alot": 282, "manfaat": 283, "basah": 284, "oleh": 285, "untung": 286, "prosesnya": 287, "goreng": 288, "ekspedisi": 289, "tetapi": 290, "telat": 291, "keju": 292, "coklat": 293, "nanti": 294, "keadaan": 295, "soalnya": 296, "sehari": 297, "porsi": 298, "almond": 299, "tahun": 300, "promo": 301, "asi": 302, "besok": 303, "empuk": 304, "layanan": 305, "sempat": 306, "kulit": 307, "perlu": 308, "komplain": 309, "kangen": 310, "malah": 311, "air": 312, "as": 313, "pelayan": 314, "saran": 315, "sempurna": 316, "tokped": 317, "gp": 318, "bersih": 319, "anteraja": 320, "tokopedia": 321, "gambar": 322, "sehingga": 323, "merek": 324, "lengkap": 325, "bagaimana": 326, "kerupuk": 327, "digoreng": 328, "diperhatikan": 329, "harusnya": 330, "supaya": 331, "nasi": 332, "mudah": 333, "tanpa": 334, "bumbu": 335, "sebelumnya": 336, "kurirnya": 337, "is": 338, "hehehe": 339, "sehat": 340, "apek": 341, "apalagi": 342, "ngomong": 343, "tipis": 344, "takut": 345, "cumi": 346, "jujur": 347, "berkah": 348, "ditulis": 349, "antar": 350, "bakalan": 351, "sejak": 352, "bicara": 353, "ketika": 354, "salad": 355, "gosong": 356, "minggu": 357, "snack": 358, "bakal": 359, "lihat": 360, "abon": 361, "sapi": 362, "cuman": 363, "gram": 364, "telah": 365, "sedih": 366, "permintaan": 367, "begitu": 368, "si": 369, "cantik": 370, "membantu": 371, "kota": 372, "senang": 373, "bilang": 374, "tunggu": 375, "bayar": 376, "in": 377, "uang": 378, "mengecewakan": 379, "pembeli": 380, "juice": 381, "hati": 382, "namun": 383, "penuh": 384, "dikemas": 385, "dingin": 386, "sengaja": 387, "mahal": 388, "bumbunya": 389, "masakan": 390, "kapok": 391, "sekian": 392, "alah": 393, "ah": 394, "untungnya": 395, "berbicara": 396, "daging": 397, "tokonya": 398, "pada": 399, "tekstur": 400, "warna": 401, "aneh": 402, "dong": 403, "nih": 404, "diperbaiki": 405, "ukuran": 406, "madu": 407, "lemon": 408, "saladnya": 409, "penjualnya": 410, "doang": 411, "lucu": 412, "gorengnya": 413, "kita": 414, "mini": 415, "entah": 416, "pemesanan": 417, "sampah": 418, "ditoko": 419, "kartu": 420, "sedap": 421, "sambal": 422, "janji": 423, "minimal": 424, "jus": 425, "jadinya": 426, "durian": 427, "ebi": 428, "diantar": 429, "dilihat": 430, "susah": 431, "bangun": 432, "lancar": 433, "amin": 434, "tengik": 435, "kerupuknya": 436, "terbuka": 437, "telepon": 438, "kopi": 439, "ny": 440, "keripiknya": 441, "susu": 442, "garam": 443, "basi": 444, "nunggu": 445, "penting": 446, "robek": 447, "kapan": 448, "dijual": 449, "sabtu": 450, "ku": 451, "lebaran": 452, "kriuk": 453, "makin": 454, "tujuan": 455, "botol": 456, "kalian": 457, "pilih": 458, "kopinya": 459, "hitam": 460, "kemanisan": 461, "ingin": 462, "dia": 463, "korea": 464, "roti": 465, "spesial": 466, "gulanya": 467, "menyesal": 468, "dalamnya": 469, "u": 470, "awal": 471, "juli": 472, "keburu": 473, "mentah": 474, "biji": 475, "pikir": 476, "to": 477, "kuat": 478, "setengah": 479, "ka": 480, "baso": 481, "lengket": 482, "hr": 483, "segel": 484, "catatan": 485, "te": 486, "pe": 487, "mah": 488, "sebagian": 489, "permen": 490, "segitu": 491, "ayamnya": 492, "putih": 493, "pcs": 494, "asinya": 495, "tumpeng": 496, "kena": 497, "tambahan": 498, "wkwkw": 499, "berharap": 500, "jempol": 501, "niat": 502, "jogja": 503, "hampers": 504, "badan": 505, "dibuat": 506, "vakum": 507, "lontongnya": 508, "benyek": 509, "etalase": 510, "lapak": 511, "pertahankan": 512, "sis": 513, "jualan": 514, "dominan": 515, "konsumen": 516, "semarang": 517, "oven": 518, "halus": 519, "lauk": 520, "jumat": 521, "jakarta": 522, "kelapanya": 523, "ujungnya": 524, "besoknya": 525, "bungkusan": 526, "teri": 527, "y": 528, "maupun": 529, "ucapan": 530, "ramadhan": 531, "udangnya": 532, "one": 533, "jika": 534, "gara": 535, "setia": 536, "timbanganya": 537, "punya": 538, "enek": 539, "it": 540, "meskipun": 541, "perjalanan": 542, "senin": 543, "a": 544, "ngasih": 545, "jelek": 546, "bakso": 547, "menggunakan": 548, "berhenti": 549, "hahaha": 550, "pak": 551, "cemilan": 552, "makananya": 553, "diproses": 554, "cara": 555, "siap": 556, "bagian": 557, "berbau": 558, "toples": 559, "toplesnya": 560, "jelas": 561, "butuh": 562, "terjangkau": 563, "sabar": 564, "pihak": 565, "terlihat": 566, "menikmati": 567, "durianya": 568, "diberi": 569, "diminum": 570, "juara": 571, "laris": 572, "iklan": 573, "keluar": 574, "profesional": 575, "okelah": 576, "pengalaman": 577, "mengirim": 578, "kantong": 579, "sicepat": 580, "seharusnya": 581, "maret": 582, "sungguh": 583, "transaksi": 584, "estimasi": 585, "engak": 586, "setiap": 587, "biskuit": 588, "patah": 589, "udang": 590, "pula": 591, "kek": 592, "selain": 593, "dekat": 594, "sarwendah": 595, "secara": 596, "lapis": 597, "legit": 598, "dimasak": 599, "he": 600, "tercium": 601, "asem": 602, "kulitnya": 603, "diragukan": 604, "masalah": 605, "boleh": 606, "tokocabang": 607, "iya": 608, "lewat": 609, "hambar": 610, "minuman": 611, "salmon": 612, "mentai": 613, "momomaru": 614, "kuningnya": 615, "terjaga": 616, "mei": 617, "diberikan": 618, "jigly": 619, "nastarnya": 620, "oklah": 621, "mdh": 622, "terlambat": 623, "mengirimnya": 624, "krupuknya": 625, "jambal": 626, "pokonya": 627, "bad": 628, "pahitnya": 629, "sep": 630, "info": 631, "bakar": 632, "nori": 633, "kiamboy": 634, "gila": 635, "suruh": 636, "of": 637, "hm": 638, "jadul": 639, "my": 640, "ontime": 641, "jawab": 642, "aci": 643, "lupa": 644, "maksimal": 645, "lempar": 646, "madunya": 647, "normal": 648, "pedasnya": 649, "menurun": 650, "kelamaan": 651, "kejadian": 652, "amis": 653, "bulan": 654, "panjang": 655, "brownies": 656, "chewy": 657, "dark": 658, "kismis": 659, "wkwkwk": 660, "siangnya": 661, "kripiknya": 662, "solo": 663, "karak": 664, "konsumsi": 665, "ketagihan": 666, "da": 667, "double": 668, "jawaban": 669, "dropship": 670, "kebun": 671, "mereka": 672, "mulai": 673, "usaha": 674, "lembab": 675, "br": 676, "corniche": 677, "marshmalow": 678, "pink": 679, "istri": 680, "keasaman": 681, "responsif": 682, "berat": 683, "keberapa": 684, "pengirimannya": 685, "nice": 686, "buru": 687, "dimasukan": 688, "kulkas": 689, "parkir": 690, "kembang": 691, "kaki": 692, "lima": 693, "duit": 694, "online": 695, "bolen": 696, "natal": 697, "dsn": 698, "tambah": 699, "on": 700, "kenyal": 701, "diatas": 702, "vanila": 703, "nanasnya": 704, "om": 705, "padat": 706, "kuacinya": 707, "apapun": 708, "rumput": 709, "laut": 710, "rutin": 711, "kebanyakan": 712, "campuranya": 713, "kan": 714, "bebas": 715, "surabaya": 716, "mochi": 717, "seminggu": 718, "canele": 719, "rebon": 720, "gula": 721, "fotonya": 722, "lembek": 723, "rapuh": 724, "checkout": 725, "bandeng": 726, "es": 727, "tumpah": 728, "gelap": 729, "bentuknya": 730, "tampilannya": 731, "tampilan": 732, "pesto": 733, "sari": 734, "enakan": 735, "ngemil": 736, "namanya": 737, "sakit": 738, "itupun": 739, "kosong": 740, "tulisan": 741, "cuanki": 742, "harinya": 743, "mba": 744, "bubuk": 745, "bu": 746, "masuk": 747, "deg": 748, "kecuali": 749, "segi": 750, "ngunyah": 751, "sudahlah": 752, "adalah": 753, "pelanggan": 754, "gabus": 755, "diskon": 756, "cuka": 757, "standart": 758, "usahanya": 759, "masaknya": 760, "meletus": 761, "irisan": 762, "jasa": 763, "track": 764, "menuju": 765, "bantu": 766, "kepake": 767, "terenak": 768, "sebelah": 769, "mil": 770, "pure": 771, "rekomended": 772, "dirumah": 773, "cancel": 774, "this": 775, "healthy": 776, "keterangan": 777, "hasilnya": 778, "kakak": 779, "tenaga": 780, "kecut": 781, "bawah": 782, "minyak": 783, "indonesia": 784, "berlabel": 785, "pindah": 786, "percaya": 787, "sumpah": 788, "tiga": 789, "plastiknya": 790, "retak": 791, "bolong": 792, "nilai": 793, "tinggi": 794, "produksi": 795, "ditangani": 796, "pie": 797, "pokok": 798, "hilang": 799, "dibantu": 800, "dipesan": 801, "langganan": 802, "terkenal": 803, "sebagus": 804, "selesai": 805, "tua": 806, "lokasi": 807, "meleleh": 808, "konsisten": 809, "libur": 810, "bolu": 811, "singkong": 812, "terinya": 813, "barangnya": 814, "pickup": 815, "ampir": 816, "set": 817, "map": 818, "kurangi": 819, "bakpia": 820, "bekasi": 821, "emping": 822, "harganya": 823, "susunya": 824, "didalam": 825, "wajar": 826, "selanjutnya": 827, "pagar": 828, "bali": 829, "saus": 830, "terbelah": 831, "ragu": 832, "terkontaminasi": 833, "sesuatu": 834, "anda": 835, "baiknya": 836, "dijadikan": 837, "penjelasan": 838, "transparan": 839, "x": 840, "menit": 841, "kasus": 842, "medan": 843, "bakpianya": 844, "nempel": 845, "cuminya": 846, "ayam": 847, "balut": 848, "campuran": 849, "kadang": 850, "sich": 851, "diharapkan": 852, "bareng": 853, "bersama": 854, "sing": 855, "diolah": 856, "asapnya": 857, "datangnya": 858, "ebinya": 859, "sebenernya": 860, "aroma": 861, "bosan": 862, "sebanding": 863, "kebocoran": 864, "masa": 865, "baca": 866, "kasi": 867, "balado": 868, "dipercaya": 869, "membatalkan": 870, "terutama": 871, "batal": 872, "edisi": 873, "ig": 874, "gini": 875, "ml": 876, "insyalah": 877, "nikmat": 878, "campur": 879, "buah": 880, "tumben": 881, "dibanding": 882, "masak": 883, "roselanya": 884, "tempat": 885, "lalu": 886, "kentangnya": 887, "terkesan": 888, "minumnya": 889, "kejunya": 890, "selama": 891, "menjaga": 892, "mengumpal": 893, "diabetes": 894, "ukuranya": 895, "gepeng": 896, "dipakai": 897, "dipickup": 898, "refund": 899, "dibuang": 900, "ingat": 901, "panas": 902, "cabenya": 903, "sayur": 904, "kesukaan": 905, "bq": 906, "basrengnya": 907, "persediaan": 908, "lauknya": 909, "uk": 910, "p": 911, "almondnya": 912, "empingnya": 913, "bonusnya": 914, "ter": 915, "tulus": 916, "potion": 917, "instan": 918, "bingung": 919, "esok": 920, "kendala": 921, "momoiro": 922, "doyan": 923, "dichat": 924, "kadar": 925, "datenya": 926, "wa": 927, "pingin": 928, "insha": 929, "cucut": 930, "pesanya": 931, "chatime": 932, "gemblongnya": 933, "ketanya": 934, "medok": 935, "kadaluwarsa": 936, "jan": 937, "memakai": 938, "boksnya": 939, "al": 940, "sampainya": 941, "poko": 942, "lidinya": 943, "ms": 944, "dikasinya": 945, "kos": 946, "dikonsumsi": 947, "sop": 948, "sekuriti": 949, "bts": 950, "jagung": 951, "klop": 952, "unik": 953, "biscuitnya": 954, "umumnya": 955, "restok": 956, "menelan": 957, "market": 958, "mirip": 959, "beard": 960, "papa": 961, "sus": 962, "liking": 963, "light": 964, "heran": 965, "tumpengnya": 966, "wismanya": 967, "buahnya": 968, "tanggung": 969, "rubah": 970, "mengganti": 971, "huhu": 972, "kuaci": 973, "frenya": 974, "dikartunya": 975, "from": 976, "dicatatan": 977, "main": 978, "homemade": 979, "dibeli": 980, "langananm": 981, "abonya": 982, "efektif": 983, "kekurangan": 984, "lahir": 985, "bathin": 986, "paslah": 987, "terpercaya": 988, "kebelakang": 989, "tebel": 990, "seleksi": 991, "ketiga": 992, "kempat": 993, "nulis": 994, "kesalahan": 995, "pebgiriman": 996, "kotor": 997, "pesenan": 998, "berlendir": 999, "kepanasan": 1000, "styrofoam": 1001, "sebulan": 1002, "melimpah": 1003, "bm": 1004, "idem": 1005, "atas": 1006, "dicancel": 1007, "nov": 1008, "cokelat": 1009, "sentosa": 1010, "desain": 1011, "beruang": 1012, "pantatnya": 1013, "bearly": 1014, "baker": 1015, "bawel": 1016, "istimevah": 1017, "meiji": 1018, "cracker": 1019, "perbaiki": 1020, "secinta": 1021, "seleros": 1022, "lemas": 1023, "pasar": 1024, "kaku": 1025, "hihihi": 1026, "jahe": 1027, "cucok": 1028, "meong": 1029, "ngasal": 1030, "pelaksanaan": 1031, "diulangi": 1032, "nge": 1033, "akun": 1034, "dropshiper": 1035, "kismisnya": 1036, "huwehehe": 1037, "terbiasa": 1038, "pilus": 1039, "cikur": 1040, "tingkat": 1041, "diatur": 1042, "menyesuaikan": 1043, "harang": 1044, "mite": 1045, "choco": 1046, "mocha": 1047, "eniwei": 1048, "informasi": 1049, "euy": 1050, "coca": 1051, "cola": 1052, "tepat": 1053, "bund": 1054, "infokan": 1055, "khilaf": 1056, "medenya": 1057, "akibat": 1058, "disimpan": 1059, "keseratus": 1060, "hadiah": 1061, "motor": 1062, "endul": 1063, "bentuk": 1064, "tujuh": 1065, "proteksinya": 1066, "diacungi": 1067, "kw": 1068, "mesti": 1069, "pilihin": 1070, "pelan": 1071, "kembalikan": 1072, "sisanya": 1073, "ngetik": 1074, "huruf": 1075, "membayar": 1076, "rs": 1077, "adain": 1078, "krmnya": 1079, "smal": 1080, "bergembira": 1081, "bx": 1082, "gimana": 1083, "jigae": 1084, "utamanya": 1085, "rebutan": 1086, "wysmanya": 1087, "filing": 1088, "nanas": 1089, "kejel": 1090, "ekpedisi": 1091, "mendominasi": 1092, "tomat": 1093, "ceri": 1094, "sepahit": 1095, "pusing": 1096, "sebetulnya": 1097, "cerdas": 1098, "dibohongin": 1099, "oreo": 1100, "big": 1101, "se": 1102, "meriah": 1103, "subhanalah": 1104, "packnya": 1105, "camilan": 1106, "seadanya": 1107, "rabu": 1108, "kelasnya": 1109, "rupa": 1110, "potongan": 1111, "terluv": 1112, "kacau": 1113, "enaknya": 1114, "late": 1115, "gradenya": 1116, "brand": 1117, "tetangga": 1118, "lontong": 1119, "warmderland": 1120, "restock": 1121, "cus": 1122, "kalap": 1123, "waktunya": 1124, "otak": 1125, "tadi": 1126, "potong": 1127, "mencair": 1128, "total": 1129, "bandengnya": 1130, "kerabat": 1131, "donatnya": 1132, "bonyok": 1133, "bahan": 1134, "kertas": 1135, "sulit": 1136, "wasabi": 1137, "ive": 1138, "had": 1139, "disegel": 1140, "kebersihan": 1141, "dipilih": 1142, "up": 1143, "grabexpresnya": 1144, "dikeluarkan": 1145, "ocha": 1146, "rapimakananya": 1147, "however": 1148, "was": 1149, "litle": 1150, "salads": 1151, "portion": 1152, "kimia": 1153, "esence": 1154, "gplah": 1155, "perut": 1156, "kamis": 1157, "email": 1158, "angin": 1159, "alias": 1160, "tadinya": 1161, "gamau": 1162, "maklumin": 1163, "kabar": 1164, "tanyain": 1165, "kesokan": 1166, "ambil": 1167, "ampasnya": 1168, "kunyit": 1169, "asamnya": 1170, "tempenya": 1171, "labelnya": 1172, "rudy": 1173, "wedang": 1174, "uwuh": 1175, "kartika": 1176, "gojek": 1177, "gemesh": 1178, "bgtdpt": 1179, "paperbag": 1180, "ma": 1181, "kartuny": 1182, "diprosesnya": 1183, "terfavorit": 1184, "acinya": 1185, "merubah": 1186, "value": 1187, "reply": 1188, "kenari": 1189, "tidur": 1190, "bdn": 1191, "oncomnya": 1192, "tebalnya": 1193, "separuh": 1194, "oncom": 1195, "rainbow": 1196, "jely": 1197, "pengawet": 1198, "krucil": 1199, "yogya": 1200, "dpaksa": 1201, "digencet": 1202, "boxnya": 1203, "pengok": 1204, "boromonya": 1205, "pastry": 1206, "wanginya": 1207, "mengoda": 1208, "hokaido": 1209, "dimari": 1210, "h": 1211, "bosku": 1212, "selu": 1213, "tekanan": 1214, "gas": 1215, "duluan": 1216, "mekar": 1217, "gelasnya": 1218, "hasil": 1219, "sayuran": 1220, "rbu": 1221, "sayuranya": 1222, "toping": 1223, "kn": 1224, "nambahin": 1225, "tuna": 1226, "saosnya": 1227, "laporkan": 1228, "ditanggung": 1229, "terucap": 1230, "memaki": 1231, "pesawat": 1232, "makasar": 1233, "terburu": 1234, "secepat": 1235, "kilat": 1236, "timbangan": 1237, "spec": 1238, "kepala": 1239, "pacar": 1240, "diorder": 1241, "yak": 1242, "ngembang": 1243, "ovltine": 1244, "coklatnya": 1245, "dibandingkan": 1246, "rencengan": 1247, "warung": 1248, "dicemil": 1249, "obat": 1250, "angap": 1251, "bagi": 1252, "peduli": 1253, "kesehatan": 1254, "sejati": 1255, "riki": 1256, "bird": 1257, "nest": 1258, "asumsi": 1259, "ditanyain": 1260, "balas": 1261, "stikernya": 1262, "nich": 1263, "serta": 1264, "pemberitahuanya": 1265, "diandalkan": 1266, "i": 1267, "luv": 1268, "nut": 1269, "eating": 1270, "breakfast": 1271, "usualy": 1272, "masam": 1273, "keteranganya": 1274, "alamat": 1275, "caranya": 1276, "lover": 1277, "bublenya": 1278, "oishi": 1279, "toza": 1280, "segera": 1281, "ekstra": 1282, "gigitnya": 1283, "masing": 1284, "item": 1285, "enteng": 1286, "tipe": 1287, "keluarga": 1288, "diabet": 1289, "baksonya": 1290, "lazis": 1291, "ampunya": 1292, "tertolong": 1293, "dicuci": 1294, "mengendap": 1295, "serasa": 1296, "sopan": 1297, "kehitung": 1298, "botanical": 1299, "sanitizer": 1300, "yuk": 1301, "kunjungi": 1302, "chea": 1303, "apakah": 1304, "stocknya": 1305, "dagingnya": 1306, "pic": 1307, "pancen": 1308, "tekan": 1309, "atiku": 1310, "lelelelelelelelelelelelelelelelelelelelelelelelelelelele": 1311, "mao": 1312, "kelain": 1313, "buktin": 1314, "aje": 1315, "man": 1316, "ngurangin": 1317, "bruntusan": 1318, "bolunya": 1319, "jatuh": 1320, "cinta": 1321, "dech": 1322, "dibuble": 1323, "dalemnya": 1324, "wadah": 1325, "nutup": 1326, "disolasi": 1327, "lakban": 1328, "terbungkus": 1329, "olshop": 1330, "dinginkan": 1331, "bermanfaat": 1332, "umi": 1333, "jember": 1334, "cuangki": 1335, "lebak": 1336, "bulus": 1337, "rentak": 1338, "denpasar": 1339, "penampilan": 1340, "kantor": 1341, "penerimanya": 1342, "pulang": 1343, "ketepatan": 1344, "pembungkusnya": 1345, "menyenangkan": 1346, "gandos": 1347, "ginian": 1348, "sesuia": 1349, "semalam": 1350, "mengantarkan": 1351, "topoki": 1352, "apreciated": 1353, "penyelesaianya": 1354, "tengah": 1355, "barusan": 1356, "masuknya": 1357, "depok": 1358, "berantakan": 1359, "moachi": 1360, "gemini": 1361, "basreng": 1362, "disuruh": 1363, "ceroboh": 1364, "anterajanya": 1365, "anterajanternya": 1366, "unboxing": 1367, "jualanku": 1368, "bertanggung": 1369, "kekuranganya": 1370, "bandung": 1371, "candy": 1372, "mpek": 1373, "tanggap": 1374, "vacum": 1375, "kendor": 1376, "berubah": 1377, "rentah": 1378, "berdekatan": 1379, "luber": 1380, "ditambahkan": 1381, "kuah": 1382, "membasahi": 1383, "dikirimkan": 1384, "alasan": 1385, "dihitung": 1386, "sistem": 1387, "pembayaran": 1388, "salam": 1389, "sekedar": 1390, "bag": 1391, "menambah": 1392, "cabe": 1393, "prompt": 1394, "constant": 1395, "kriu": 1396, "gendut": 1397, "menul": 1398, "buanget": 1399, "rikues": 1400, "tkp": 1401, "kelewat": 1402, "takjil": 1403, "horor": 1404, "ususnya": 1405, "sobek": 1406, "penyelamat": 1407, "mual": 1408, "muntah": 1409, "palembang": 1410, "mengirimkan": 1411, "hamil": 1412, "muda": 1413, "juragan": 1414, "wfh": 1415, "kleponya": 1416, "bismilahirahmanirahim": 1417, "lindungi": 1418, "tindakan": 1419, "keputusan": 1420, "anugerahi": 1421, "keselamatan": 1422, "dunia": 1423, "akhirat": 1424, "pantas": 1425, "kadaluarsanya": 1426, "tertimpa": 1427, "menyehatkan": 1428, "dibersihkan": 1429, "diikat": 1430, "ceceran": 1431, "berminyak": 1432, "jumbo": 1433, "its": 1434, "mari": 1435, "daerah": 1436, "kelapa": 1437, "gading": 1438, "banjir": 1439, "pangang": 1440, "bosqu": 1441, "menarik": 1442, "pesingnya": 1443, "vco": 1444, "halo": 1445, "cemilanya": 1446, "bismilahi": 1447, "walhamdulilah": 1448, "insyaallah": 1449, "jernih": 1450, "tanda": 1451, "stiker": 1452, "hinga": 1453, "membutuhkan": 1454, "expres": 1455, "judulnya": 1456, "curah": 1457, "taburan": 1458, "dibonusin": 1459, "dibakar": 1460, "semenjak": 1461, "mengasihi": 1462, "second": 1463, "rindu": 1464, "siapkan": 1465, "sedihnya": 1466, "matcha": 1467, "tuhan": 1468, "yesus": 1469, "memberkati": 1470, "gunakan": 1471, "keduanya": 1472, "kotaknya": 1473, "higienisnya": 1474, "seandainya": 1475, "keadanya": 1476, "yaitu": 1477, "kemungkinanya": 1478, "tersebut": 1479, "ikuti": 1480, "jangankan": 1481, "dibaca": 1482, "feb": 1483, "d": 1484, "modus": 1485, "seolah": 1486, "perduli": 1487, "calon": 1488, "itikad": 1489, "merasa": 1490, "diuntungkan": 1491, "pembenaran": 1492, "terjamin": 1493, "transaksinya": 1494, "ribu": 1495, "soal": 1496, "lem": 1497, "kebuka": 1498, "pulau": 1499, "lho": 1500, "ditolak": 1501, "cairan": 1502, "bublewarp": 1503, "ber": 1504, "almon": 1505, "semisal": 1506, "suvenir": 1507, "masalahnya": 1508, "diselesaikan": 1509, "asuransi": 1510, "pergantian": 1511, "strategi": 1512, "terulang": 1513, "tanggapan": 1514, "serupa": 1515, "dirugikan": 1516, "antri": 1517, "cupnya": 1518, "pancking": 1519, "seharga": 1520, "sliming": 1521, "tea": 1522, "dibawah": 1523, "gumpalan": 1524, "akurasi": 1525, "guys": 1526, "terbayarkan": 1527, "packingngya": 1528, "gmn": 1529, "overprice": 1530, "pinggiran": 1531, "mending": 1532, "sekalian": 1533, "monica": 1534, "alfamart": 1535, "inshalah": 1536, "berbentuk": 1537, "orderjumat": 1538, "pabriknya": 1539, "umum": 1540, "matang": 1541, "ditengahnya": 1542, "bgks": 1543, "sumatera": 1544, "sejauha": 1545, "minus": 1546, "entaraja": 1547, "pelepah": 1548, "me": 1549, "teksturnya": 1550, "karton": 1551, "buar": 1552, "masalahlah": 1553, "jualannya": 1554, "bersaing": 1555, "caramel": 1556, "buter": 1557, "sebagai": 1558, "pembawa": 1559, "mengevaluasi": 1560, "grab": 1561, "demikian": 1562, "kayu": 1563, "barakalah": 1564, "atasnya": 1565, "kebagian": 1566, "maicih": 1567, "kepastian": 1568, "haha": 1569, "karet": 1570, "beruntung": 1571, "ketemu": 1572, "high": 1573, "sepet": 1574, "khasiat": 1575, "much": 1576, "wel": 1577, "santap": 1578, "pouchnya": 1579, "biarlah": 1580, "kompetitif": 1581, "dilupakan": 1582, "kenangan": 1583, "indah": 1584, "mu": 1585, "tinggalah": 1586, "mimpi": 1587, "lose": 1588, "ciyus": 1589, "mengurangi": 1590, "citra": 1591, "mengobati": 1592, "lumpia": 1593, "josh": 1594, "gandhos": 1595, "almonya": 1596, "ekspetasi": 1597, "lebihan": 1598, "kiloanya": 1599, "lgagustus": 1600, "mana": 1601, "obral": 1602, "kejar": 1603, "modal": 1604, "maunya": 1605, "merekomendasikan": 1606, "pdng": 1607, "reseler": 1608, "suplemen": 1609, "dede": 1610, "wisman": 1611, "dikurangi": 1612, "terpenuhi": 1613, "pesenya": 1614, "toge": 1615, "jiwa": 1616, "naujubilah": 1617, "mencret": 1618, "sok": 1619, "sokan": 1620, "extra": 1621, "rb": 1622, "seupil": 1623, "recomed": 1624, "kemudian": 1625, "klik": 1626, "berikutnya": 1627, "kondisinya": 1628, "penyet": 1629, "juni": 1630, "depan": 1631, "gosa": 1632, "awalnya": 1633, "penasaran": 1634, "udara": 1635, "terlebih": 1636, "pisang": 1637, "ditingkatkan": 1638, "malas": 1639, "update": 1640, "status": 1641, "nutela": 1642, "melting": 1643, "dapatnya": 1644, "level": 1645, "bervariasi": 1646, "selasa": 1647, "pwrjo": 1648, "berimbas": 1649, "diadu": 1650, "cream": 1651, "membuat": 1652, "alur": 1653, "jarang": 1654, "notifikasi": 1655, "khusus": 1656, "tokopedianya": 1657, "harap": 1658, "alamatnya": 1659, "dibatalkan": 1660, "ribet": 1661, "adanya": 1662, "tulis": 1663, "dm": 1664, "dibalas": 1665, "ekspedisinya": 1666, "delish": 1667, "ringan": 1668, "patut": 1669, "merata": 1670, "berair": 1671, "sa": 1672, "tepungnya": 1673, "kedatangan": 1674, "mas": 1675, "cok": 1676, "krispi": 1677, "sedang": 1678, "sincia": 1679, "serahkan": 1680, "penerima": 1681, "keinginan": 1682, "minumanya": 1683, "chicken": 1684, "katsu": 1685, "ongkirnya": 1686, "lebihin": 1687, "utang": 1688, "deket": 1689, "donat": 1690, "sesuailah": 1691, "bdg": 1692, "kesal": 1693, "asal": 1694, "asalan": 1695, "lapisi": 1696, "sprinkles": 1697, "bulanya": 1698, "sumpia": 1699, "pokokya": 1700, "seasoning": 1701, "dinotice": 1702, "ijonya": 1703, "direkomendasikan": 1704, "bahkan": 1705, "lalapanya": 1706, "ikut": 1707, "tertekan": 1708, "lo": 1709, "bosque": 1710, "kwacinya": 1711, "tangan": 1712, "tingkatkan": 1713, "dibawa": 1714, "kepingin": 1715, "makanya": 1716, "dijalan": 1717, "pahangnya": 1718, "udahanya": 1719, "manfaatnya": 1720, "ngalir": 1721, "boster": 1722, "efeknya": 1723, "rembes": 1724, "jeruk": 1725, "hotel": 1726, "dibanyakin": 1727, "dipisah": 1728, "dicampurin": 1729, "sangking": 1730, "sdihnya": 1731, "rupanya": 1732, "trinja": 1733, "botolnya": 1734, "sebenarnya": 1735, "hayo": 1736, "seal": 1737, "by": 1738, "higienitasnya": 1739, "ojol": 1740, "khan": 1741, "andalan": 1742, "menyusui": 1743, "ternama": 1744, "snacknya": 1745, "ramai": 1746, "terimanya": 1747, "tercampur": 1748, "rata": 1749, "yakin": 1750, "garlic": 1751, "power": 1752, "hydrofarm": 1753, "luka": 1754, "menutup": 1755, "rendah": 1756, "kenyang": 1757, "maha": 1758, "dahsyat": 1759, "wagyu": 1760, "kelas": 1761, "terkocok": 1762, "model": 1763, "kurangnya": 1764, "menerima": 1765, "masukan": 1766, "memes": 1767, "berwarna": 1768, "kehitaman": 1769, "berjamur": 1770, "solusi": 1771, "dana": 1772, "diminta": 1773, "artinya": 1774, "buang": 1775, "bensin": 1776, "mudahan": 1777, "tanks": 1778, "selertokopedia": 1779, "sukes": 1780, "memesan": 1781, "ordernya": 1782, "ganjel": 1783, "sebaiknya": 1784, "pagian": 1785, "cust": 1786, "kemalaman": 1787, "yups": 1788, "team": 1789, "terkirim": 1790, "berhasil": 1791, "akhir": 1792, "neh": 1793, "psg": 1794, "molenya": 1795, "baby": 1796, "karaknya": 1797, "mengembang": 1798, "dijemur": 1799, "bunganya": 1800, "diseduh": 1801, "warnanya": 1802, "choipan": 1803, "imlek": 1804, "tamu": 1805, "alhasil": 1806, "wajib": 1807, "cobain": 1808, "na": 1809, "rasanaya": 1810, "padang": 1811, "baladonya": 1812, "serley": 1813, "pedia": 1814, "way": 1815, "dipakein": 1816, "biaya": 1817, "semut": 1818, "dikulkas": 1819, "contoh": 1820, "jusnya": 1821, "ngefek": 1822, "pendek": 1823, "patahan": 1824, "mgk": 1825, "ketinggalan": 1826, "habisin": 1827, "sekoteng": 1828, "jaman": 1829, "suami": 1830, "pa": 1831, "timun": 1832, "sawi": 1833, "jajang": 1834, "ramyeon": 1835, "mulus": 1836, "michin": 1837, "mangut": 1838, "pari": 1839, "asap": 1840, "digelas": 1841, "dibotol": 1842, "ditutup": 1843, "airnya": 1844, "dicampur": 1845, "merah": 1846, "ak": 1847, "frezer": 1848, "dibdg": 1849, "nyicipin": 1850, "madep": 1851, "lurang": 1852, "tepung": 1853, "coy": 1854, "bawangnta": 1855, "kutunya": 1856, "eksekusi": 1857, "kuning": 1858, "ati": 1859, "ampla": 1860, "perkedel": 1861, "urap": 1862, "telur": 1863, "orek": 1864, "tempe": 1865, "sambalnya": 1866, "fiber": 1867, "berguna": 1868, "memperbaiki": 1869, "pencernan": 1870, "mewah": 1871, "mendarat": 1872, "tap": 1873, "janlupasholwat": 1874, "kurangbagus": 1875, "terhits": 1876, "nanya": 1877, "kt": 1878, "nyatanya": 1879, "syukur": 1880, "oder": 1881, "dikemut": 1882, "mempunyai": 1883, "inisiatif": 1884, "menangulangi": 1885, "potensi": 1886, "hambatan": 1887, "samosanya": 1888, "terpaksa": 1889, "tersegar": 1890, "menurutku": 1891, "dibagi": 1892, "menjadi": 1893, "per": 1894, "sesampainya": 1895, "mengembung": 1896, "meledak": 1897, "guncangan": 1898, "kehilangan": 1899, "jeruknya": 1900, "fave": 1901, "ibu": 1902, "hp": 1903, "jaga": 1904, "imun": 1905, "tubuh": 1906, "berthn": 1907, "acurate": 1908, "t": 1909, "premium": 1910, "taunya": 1911, "impresive": 1912, "kaka": 1913, "kremes": 1914, "terhitung": 1915, "sejujurnya": 1916, "pinpoint": 1917, "notice": 1918, "usah": 1919, "dibahas": 1920, "daebak": 1921, "ditawarkan": 1922, "safety": 1923, "diajak": 1924, "urgent": 1925, "rambaknya": 1926, "o": 1927, "membuka": 1928, "september": 1929, "membaui": 1930, "menyeruak": 1931, "cicip": 1932, "mulut": 1933, "kebalik": 1934, "jepang": 1935, "jamon": 1936, "ngehindarin": 1937, "mag": 1938, "sahur": 1939, "stufs": 1940, "shipment": 1941, "drama": 1942, "aromanya": 1943, "carot": 1944, "tips": 1945, "toped": 1946, "seh": 1947, "sambelnya": 1948, "terasi": 1949, "uleg": 1950, "fina": 1951, "ngerti": 1952, "pakainopor": 1953, "pelapak": 1954, "komunikasi": 1955, "cuankie": 1956, "chizu": 1957, "keselurahan": 1958, "sadis": 1959, "hujan": 1960, "buatnya": 1961, "bae": 1962, "pax": 1963, "tanggalnya": 1964, "beter": 1965, "with": 1966, "ice": 1967, "usahain": 1968, "ponya": 1969, "senjata": 1970, "jalan": 1971, "klaim": 1972, "eror": 1973, "ditahan": 1974, "gods": 1975, "cup": 1976, "plain": 1977, "bantet": 1978, "kemana": 1979, "tertusuk": 1980, "langgan": 1981, "dos": 1982, "acur": 1983, "rebusnya": 1984, "stock": 1985, "bales": 1986, "expedisi": 1987, "konfirmasi": 1988, "asemnya": 1989, "gatotnya": 1990, "direndam": 1991, "dikukus": 1992, "repot": 1993, "sekilas": 1994, "ditambah": 1995, "atur": 1996, "sayurnya": 1997, "berikut": 1998, "probiotik": 1999, "alami": 2000, "marmer": 2001, "kucoba": 2002, "yas": 2003, "pienya": 2004, "bunch": 2005, "gag": 2006, "brambang": 2007, "laman": 2008, "disiapkan": 2009, "rmhnya": 2010, "bakerynya": 2011, "kontak": 2012, "bersalah": 2013, "hampir": 2014, "dingatkan": 2015, "bulat": 2016, "ulir": 2017, "dekor": 2018, "renyahpackingnya": 2019, "tampak": 2020, "rotinya": 2021, "alasanya": 2022, "menginformasikan": 2023, "bahwa": 2024, "keterlambatan": 2025, "lotus": 2026, "biscof": 2027, "kebutuhan": 2028, "rentan": 2029, "kerusakan": 2030, "apabila": 2031, "terjadi": 2032, "umur": 2033, "beri": 2034, "expire": 2035, "menjelang": 2036, "nd": 2037, "halu": 2038, "naik": 2039, "rencana": 2040, "diva": 2041, "uwu": 2042, "setidaknya": 2043, "lidah": 2044, "pemesana": 2045, "racikanya": 2046, "spertinya": 2047, "berbeda": 2048, "encer": 2049, "dipaket": 2050, "daun": 2051, "ed": 2052, "ups": 2053, "diinfokan": 2054, "otomatis": 2055, "terguncang": 2056, "zona": 2057, "perang": 2058, "adzan": 2059, "maghrib": 2060, "bublewarpnya": 2061, "anterajasangat": 2062, "ajar": 2063, "dilempar": 2064, "kedalam": 2065, "melewati": 2066, "pergi": 2067, "simple": 2068, "kedepanya": 2069, "agar": 2070, "norinya": 2071, "jadwal": 2072, "rasaya": 2073, "kaget": 2074, "pesananku": 2075, "lacak": 2076, "terupdate": 2077, "telp": 2078, "pribadi": 2079, "record": 2080, "slicenya": 2081, "banyakan": 2082, "tuanks": 2083, "dipercepat": 2084, "pengen": 2085, "bismilah": 2086, "numpang": 2087, "bet": 2088, "jamuran": 2089}